{"httpProtocol":"HTTP/1.1","clientAcceptEncoding":"gzip, deflate, br","requestPriority":"","edgeRequestKeepAliveStatus":1,"requestHeaderNames":{},"clientTcpRtt":103,"clientQuicRtt":0,"colo":"SIN","asn":4788,"asOrganization":"INTERNET SERVICE PROVIDER, MALAYSIA","country":"MY","isEUCountry":false,"city":"Kampung Baru Balakong","continent":"AS","region":"Selangor","regionCode":"10","timezone":"Asia/Kuala_Lumpur","longitude":"101.74714","latitude":"3.02938","postalCode":"44110","tlsVersion":"TLSv1.3","tlsCipher":"AEAD-AES256-GCM-SHA384","tlsClientRandom":"0Cwdg28osSBacdFEuyRn0vfuKzQd518eB15B+ohFy2Y=","tlsClientCiphersSha1":"kXrN3VEKDdzz2cPKTQaKzpxVTxQ=","tlsClientExtensionsSha1":"1eY97BUYYO8vDaTfHQywB1pcNdM=","tlsClientExtensionsSha1Le":"u4wtEMFQBY18l3BzHAvORm+KGRw=","tlsExportedAuthenticator":{"clientHandshake":"47009ba6acf053600dbc4d11376af666af95d9735ced0b1a5eafc588ffdf61d4f0d37cbedb14f71462c463231ce16db2","serverHandshake":"8e8466ce693a1bb6f819da58442b2e539b5e46acd04a458c6cf62be121d7c92e31f5163ae7f0acde00126792902e65c4","clientFinished":"e40199dc0d6c1eff4fc58c12a5a425732818fecfcec27ce2e077ada1d9e90f85f14c325abbc0f20021871d33b2056269","serverFinished":"2cb2697ac5a659768c28b465a0e0958d8a25ed3a7f13c9fcaaf1d3d0c738d946c8cbfbb8d16dc1c99cdaae4911f28cd7"},"tlsClientHelloLength":"1605","tlsClientAuth":{"certPresented":"0","certVerified":"NONE","certRevoked":"0","certIssuerDN":"","certSubjectDN":"","certIssuerDNRFC2253":"","certSubjectDNRFC2253":"","certIssuerDNLegacy":"","certSubjectDNLegacy":"","certSerial":"","certIssuerSerial":"","certSKI":"","certIssuerSKI":"","certFingerprintSHA1":"","certFingerprintSHA256":"","certNotBefore":"","certNotAfter":"","certRFC9440":"","certRFC9440TooLarge":false,"certChainRFC9440":"","certChainRFC9440TooLarge":false},"verifiedBotCategory":"","edgeL4":{"deliveryRate":19229},"botManagement":{"corporateProxy":false,"verifiedBot":false,"jsDetection":{"passed":false},"staticResource":false,"detectionIds":{},"score":99}}